{
  "defaultSeverity": "error",
  "extends": [
    "tslint:recommended",
    "tslint-eslint-rules",
    "tslint-react"
  ],
  "rules": {
    "array-type": [true, "array"],
    "callable-types": [false],
    "eofline": false,
    "interface-name": false,
    "interface-over-type-literal": false,
    "jsx-boolean-value": false,
    "jsx-curly-spacing": [true, "never"],
    "jsx-equals-spacing": [true, "never"],
    "jsx-no-lambda": false,
    "jsx-no-multiline-js": false,
    "jsx-wrap-multiline": true,
    "match-default-export-name": true,
    "max-classes-per-file": false,
    "no-console": false,
    "no-invalid-this": true,
    "no-shadowed-variable": true,
    "no-string-literal": false,
    "no-unused-variable": true,
    "object-curly-spacing": [true, "never"],
    "object-literal-key-quotes": [true, "as-needed"],
    "object-literal-sort-keys": false,
    "ordered-imports": false,
    "quotemark": [true, "single", "avoid-escape", "jsx-single"],
    "trailing-comma": [true, {"multiline": "never", "singleline": "never"}]
  }
}
